[
  {
    "unit_id": 9001,
    "ref": "1 Kings 3:16",
    "hebrew_text": "אָז תָּבֹאנָה שְׁתַּיִם נָשִׁים זֹנֹות אֶל־הַמֶּלֶךְ וַתַּעֲמֹדְנָה לְפָנָיו׃"
  },
  {
    "unit_id": 9002,
    "ref": "1 Kings 3:17",
    "hebrew_text": "וַתֹּאמֶר הָאִשָּׁה הַאַחַת בִּי אֲדֹנִי אֲנִי וְהָאִשָּׁה הַזֹּאת יֹשְׁבֹת בְּבַיִת אֶחָד וָאֵלֵד עִמָּהּ בַּבָּיִת׃"
  },
  {
    "unit_id": 9003,
    "ref": "1 Kings 3:18",
    "hebrew_text": "וַיְהִי בַּיּוֹם הַשְּׁלִישִׁי לְלִדְתִּי וַתֵּלֶד גַּם־הָאִשָּׁה הַזֹּאת וַאֲנַחְנוּ יַחְדָּו אֵין־זָר אִתָּנוּ בַּבַּיִת זוּלָתִי שְׁתַּיִם־אֲנַחְנוּ בַּבָּיִת׃"
  },
  {
    "unit_id": 9004,
    "ref": "1 Kings 3:19",
    "hebrew_text": "וַיָּמָת בֶּן־הָאִשָּׁה הַזֹּאת לָיְלָה אֲשֶׁר שָׁכְבָה עָלָיו׃"
  },
  {
    "unit_id": 9005,
    "ref": "1 Kings 3:20",
    "hebrew_text": "וַתָּקָם בְּתוֹךְ הַלַּיְלָה וַתִּקַּח אֶת־בְּנִי מֵאֶצְלִי וַאֲמָתְךָ יְשֵׁנָה וַתַּשְׁכִּיבֵהוּ בְּחֵיקָהּ וְאֶת־בְּנָהּ הַמֵּת הִשְׁכִּיבָה בְחֵיקִי׃"
  },
  {
    "unit_id": 9006,
    "ref": "1 Kings 3:21",
    "hebrew_text": "וָאָקֻם בַּבֹּקֶר לְהֵינִיק אֶת־בְּנִי וְהִנֵּה־מֵת וָאֶתְבּוֹנֵן אֵלָיו בַּבֹּקֶר וְהִנֵּה לֹא־הָיָה בְנִי אֲשֶׁר יָלָדְתִּי׃"
  },
  {
    "unit_id": 9007,
    "ref": "1 Kings 3:22",
    "hebrew_text": "וַתֹּאמֶר הָאִשָּׁה הָאַחֶרֶת לֹא כִי בְּנִי הַחַי וּבְנֵךְ הַמֵּת וְזֹאת אֹמֶרֶת לֹא כִי בְּנֵךְ הַמֵּת וּבְנִי הַחָי וַתְּדַבֵּרְנָה לִפְנֵי הַמֶּלֶךְ׃"
  },
  {
    "unit_id": 9008,
    "ref": "1 Kings 10:1",
    "hebrew_text": "וּמַלְכַּת־שְׁבָא שֹׁמַעַת אֶת־שֵׁמַע שְׁלֹמֹה לְשֵׁם יְהוָה וַתָּבֹא לְנַסֹּתֹו בְּחִידֹות׃"
  },
  {
    "unit_id": 9009,
    "ref": "1 Kings 10:2",
    "hebrew_text": "וַתָּבֹא יְרוּשָׁלְַמָה בְּחַיִל כָּבֵד מְאֹד גְּמַלִּים נֹשְׂאִים בְּשָׂמִים וְזָהָב רַב־מְאֹד וְאֶבֶן יְקָרָה וַתָּבֹא אֶל־שְׁלֹמֹה וַתְּדַבֵּר אֵלָיו אֵת כָּל־אֲשֶׁר הָיָה עִם־לְבָבָהּ׃"
  },
  {
    "unit_id": 9010,
    "ref": "1 Kings 10:3",
    "hebrew_text": "וַיַּגֶּד־לָהּ שְׁלֹמֹה אֶת־כָּל־דְּבָרֶיהָ לֹא־הָיָה דָּבָר נֶעְלָם מִן־הַמֶּלֶךְ אֲשֶׁר לֹא הִגִּיד לָהּ׃"
  },
  {
    "unit_id": 9011,
    "ref": "1 Kings 10:4",
    "hebrew_text": "וַתֵּרֶא מַלְכַּת־שְׁבָא אֵת כָּל־חָכְמַת שְׁלֹמֹה וְהַבַּיִת אֲשֶׁר בָּנָה׃"
  },
  {
    "unit_id": 9012,
    "ref": "1 Kings 10:5",
    "hebrew_text": "וּמַאֲכַל שֻׁלְחָנוֹ וּמוֹשַׁב עֲבָדָיו וּמַעֲמַד מְשָׁרְתָיו וּמַלְבֻּשֵׁיהֶם וּמַשְׁקָיו וְעֹלָתוֹ אֲשֶׁר יַעֲלֶה בֵּית יְהוָה וְלֹא־הָיָה בָהּ עוֹד רוּחַ׃"
  },
  {
    "unit_id": 9013,
    "ref": "2 Kings 5:1",
    "hebrew_text": "וְנַעֲמָן שַׂר־צְבָא מֶלֶךְ־אֲרָם הָיָה אִישׁ גָּדוֹל לִפְנֵי אֲדֹנָיו וּנְשֻׂא פָנִים כִּי־בוֹ נָתַן־יְהוָה תְּשׁוּעָה לַאֲרָם וְהָאִישׁ הָיָה גִּבּוֹר חַיִל מְצֹרָע׃"
  },
  {
    "unit_id": 9014,
    "ref": "2 Kings 5:2",
    "hebrew_text": "וַאֲרָם יָצְאוּ גְדוּדִים וַיִּשְׁבּוּ מֵאֶרֶץ יִשְׂרָאֵל נַעֲרָה קְטַנָּה וַתְּהִי לִפְנֵי אֵשֶׁת נַעֲמָן׃"
  },
  {
    "unit_id": 9015,
    "ref": "2 Kings 5:3",
    "hebrew_text": "וַתֹּאמֶר אֶל־גְּבִרְתָּהּ אַחֲלֵי אֲדֹנִי לִפְנֵי הַנָּבִיא אֲשֶׁר בְּשֹׁמְרוֹן אָז יֶאֱסֹף אֹתוֹ מִצָּרַעְתּוֹ׃"
  },
  {
    "unit_id": 9016,
    "ref": "2 Kings 5:4",
    "hebrew_text": "וַיָּבֹא וַיַּגֵּד לַאדֹנָיו לֵאמֹר כָּזֹאת וְכָזֹאת דִּבְּרָה הַנַּעֲרָה אֲשֶׁר מֵאֶרֶץ יִשְׂרָאֵל׃"
  },
  {
    "unit_id": 9017,
    "ref": "2 Kings 5:5",
    "hebrew_text": "וַיֹּאמֶר מֶלֶךְ־אֲרָם לֶךְ־בֹּא וְאֶשְׁלְחָה סֵפֶר אֶל־מֶלֶךְ יִשְׂרָאֵל וַיֵּלֶךְ וַיִּקַּח בְּיָדוֹ עֶשֶׂר כִּכְּרֵי־כֶסֶף וְשֵׁשֶׁת אֲלָפִים זָהָב וְעֶשֶׂר חֲלִיפוֹת בְּגָדִים׃"
  },
  {
    "unit_id": 9018,
    "ref": "2 Kings 5:6",
    "hebrew_text": "וַיָּבֵא הַסֵּפֶר אֶל־מֶלֶךְ יִשְׂרָאֵל לֵאמֹר וְעַתָּה כְּבוֹא הַסֵּפֶר הַזֶּה אֵלֶיךָ הִנֵּה שָׁלַחְתִּי אֵלֶיךָ אֶת־נַעֲמָן עַבְדִּי וַאֲסַפְתּוֹ מִצָּרַעְתּוֹ׃"
  },
  {
    "unit_id": 9019,
    "ref": "2 Kings 5:7",
    "hebrew_text": "וַיְהִי כִּקְרֹא מֶלֶךְ־יִשְׂרָאֵל אֶת־הַסֵּפֶר וַיִּקְרַע בְּגָדָיו וַיֹּאמֶר הַאֱלֹהִים אָנִי לְהָמִית וּלְהַחֲיוֹת כִּי־זֶה שֹׁלֵחַ אֵלַי לֶאֱסֹף אִישׁ מִצָּרַעְתּוֹ כִּי דְּעוּ־נָא וּרְאוּ כִּי־מִתְאַנֶּה הוּא לִי׃"
  },
  {
    "unit_id": 9020,
    "ref": "1 Samuel 17:40",
    "hebrew_text": "וַיִּקַּח מַקְלוֹ בְּיָדוֹ וַיִּבְחַר־לוֹ חֲמִשָּׁה חַלֻּקֵי־אֲבָנִים מִן־הַנַּחַל וַיָּשֶׂם אֹתָם בִּכְלִי הָרֹעִים אֲשֶׁר־לוֹ וּבַיַּלְקוּט וְקַלְעוֹ בְיָדוֹ וַיִּגַּשׁ אֶל־הַפְּלִשְׁתִּי׃"
  },
  {
    "unit_id": 9021,
    "ref": "1 Samuel 17:41",
    "hebrew_text": "וַיֵּלֶךְ הַפְּלִשְׁתִּי הֹלֵךְ וְקָרֵב אֶל־דָּוִד וְהָאִישׁ נֹשֵׂא הַצִּנָּה לְפָנָיו׃"
  },
  {
    "unit_id": 9022,
    "ref": "1 Samuel 17:42",
    "hebrew_text": "וַיַּבֵּט הַפְּלִשְׁתִּי וַיִּרְאֶה אֶת־דָּוִד וַיִּבְזֵהוּ כִּי־הָיָה נַעַר וְאַדְמֹנִי עִם־יְפֵה מַרְאֶה׃"
  },
  {
    "unit_id": 9023,
    "ref": "1 Samuel 17:43",
    "hebrew_text": "וַיֹּאמֶר הַפְּלִשְׁתִּי אֶל־דָּוִד הֲכֶלֶב אָנֹכִי כִּי־אַתָּה בָא־אֵלַי בַּמַּקְלוֹת וַיְקַלֵּל הַפְּלִשְׁתִּי אֶת־דָּוִד בֵּאלֹהָיו׃"
  },
  {
    "unit_id": 9024,
    "ref": "1 Samuel 17:44",
    "hebrew_text": "וַיֹּאמֶר הַפְּלִשְׁתִּי אֶל־דָּוִד לְכָה אֵלַי וְאֶתְּנָה אֶת־בְּשָׂרְךָ לְעוֹף הַשָּׁמַיִם וּלְבֶהֱמַת הַשָּׂדֶה׃"
  },
  {
    "unit_id": 9025,
    "ref": "1 Samuel 17:45",
    "hebrew_text": "וַיֹּאמֶר דָּוִד אֶל־הַפְּלִשְׁתִּי אַתָּה בָּא אֵלַי בְּחֶרֶב וּבַחֲנִית וּבְכִידוֹן וְאָנֹכִי בָא־אֵלֶיךָ בְּשֵׁם יְהוָה צְבָאוֹת אֱלֹהֵי מַעַרְכוֹת יִשְׂרָאֵל אֲשֶׁר חֵרַפְתָּ׃"
  },
  {
    "unit_id": 9026,
    "ref": "1 Samuel 17:46",
    "hebrew_text": "הַיּוֹם הַזֶּה יְסַגֶּרְךָ יְהוָה בְּיָדִי וְהִכִּיתִךָ וַהֲסִרֹתִי אֶת־רֹאשְׁךָ מֵעָלֶיךָ וְנָתַתִּי פֶּגֶר מַחֲנֵה פְלִשְׁתִּים הַיּוֹם הַזֶּה לְעוֹף הַשָּׁמַיִם וּלְחַיַּת הָאָרֶץ וְיֵדְעוּ כָּל־הָאָרֶץ כִּי יֵשׁ אֱלֹהִים לְיִשְׂרָאֵל׃"
  },
  {
    "unit_id": 9027,
    "ref": "1 Samuel 17:47",
    "hebrew_text": "וְיֵדְעוּ כָּל־הַקָּהָל הַזֶּה כִּי־לֹא בְּחֶרֶב וּבַחֲנִית יְהוֹשִׁיעַ יְהוָה כִּי לַיהוָה הַמִּלְחָמָה וְנָתַן אֶתְכֶם בְּיָדֵנוּ׃"
  },
  {
    "unit_id": 9028,
    "ref": "Joshua 6:1",
    "hebrew_text": "וִירִיחוֹ סֹגֶרֶת וּמְסֻגֶּרֶת מִפְּנֵי בְּנֵי יִשְׂרָאֵל אֵין יוֹצֵא וְאֵין בָּא׃"
  },
  {
    "unit_id": 9029,
    "ref": "Joshua 6:2",
    "hebrew_text": "וַיֹּאמֶר יְהוָה אֶל־יְהוֹשֻׁעַ רְאֵה נָתַתִּי בְיָדְךָ אֶת־יְרִיחוֹ וְאֶת־מַלְכָּהּ גִּבּוֹרֵי הֶחָיִל׃"
  },
  {
    "unit_id": 9030,
    "ref": "Joshua 6:3",
    "hebrew_text": "וְסַבֹּתֶם אֶת־הָעִיר כֹּל אַנְשֵׁי הַמִּלְחָמָה הַקֵּיף אֶת־הָעִיר פַּעַם אֶחָת כֹּה תַעֲשֶׂה שֵׁשֶׁת יָמִים׃"
  },
  {
    "unit_id": 9031,
    "ref": "Joshua 6:4",
    "hebrew_text": "וְשִׁבְעָה כֹהֲנִים יִשְׂאוּ שִׁבְעָה שׁוֹפְרוֹת הַיּוֹבְלִים לִפְנֵי הָאָרוֹן וּבַיּוֹם הַשְּׁבִיעִי תָּסֹבּוּ אֶת־הָעִיר שֶׁבַע פְּעָמִים וְהַכֹּהֲנִים יִתְקְעוּ בַּשּׁוֹפָרוֹת׃"
  },
  {
    "unit_id": 9032,
    "ref": "Joshua 6:5",
    "hebrew_text": "וְהָיָה בִּמְשֹׁךְ בְּקֶרֶן הַיּוֹבֵל בְּשָׁמְעֲכֶם אֶת־קוֹל הַשּׁוֹפָר יָרִיעוּ כָל־הָעָם תְּרוּעָה גְדוֹלָה וְנָפְלָה חוֹמַת הָעִיר תַּחְתֶּיהָ וְעָלוּ הָעָם אִישׁ נֶגְדּוֹ׃"
  },
  {
    "unit_id": 9033,
    "ref": "Joshua 6:6",
    "hebrew_text": "וַיִּקְרָא יְהוֹשֻׁעַ בִּן־נוּן אֶל־הַכֹּהֲנִים וַיֹּאמֶר אֲלֵיהֶם שְׂאוּ אֶת אֲרוֹן הַבְּרִית וְשִׁבְעָה כֹהֲנִים יִשְׂאוּ שִׁבְעָה שׁוֹפְרוֹת יוֹבְלִים לִפְנֵי אֲרוֹן יְהוָה׃"
  },
  {
    "unit_id": 9034,
    "ref": "Joshua 6:7",
    "hebrew_text": "וַיֹּאמֶר אֶל־הָעָם עִבְרוּ וְסֹבּוּ אֶת־הָעִיר וְהֶחָלוּץ יַעֲבֹר לִפְנֵי אֲרוֹן יְהוָה׃"
  }
]